cdklabs/cdk_aws_iot_thing_certificate_policy/__init__.py
cdklabs/cdk_aws_iot_thing_certificate_policy/py.typed
cdklabs/cdk_aws_iot_thing_certificate_policy/_jsii/__init__.py
cdklabs/cdk_aws_iot_thing_certificate_policy/_jsii/cdk-aws-iot-thing-certificate-policy@1.0.0.jsii.tgz
cdklabs.cdk_aws_iot_thing_certificate_policy-1.0.0.dist-info/LICENSE
cdklabs.cdk_aws_iot_thing_certificate_policy-1.0.0.dist-info/METADATA
cdklabs.cdk_aws_iot_thing_certificate_policy-1.0.0.dist-info/NOTICE
cdklabs.cdk_aws_iot_thing_certificate_policy-1.0.0.dist-info/WHEEL
cdklabs.cdk_aws_iot_thing_certificate_policy-1.0.0.dist-info/top_level.txt
cdklabs.cdk_aws_iot_thing_certificate_policy-1.0.0.dist-info/RECORD
